README.md
setup.py
malnetlib/__init__.py
malnetlib/models.py
malnetlib.egg-info/PKG-INFO
malnetlib.egg-info/SOURCES.txt
malnetlib.egg-info/dependency_links.txt
malnetlib.egg-info/requires.txt
malnetlib.egg-info/top_level.txt