Metadata-Version: 2.1
Name: malnetlib
Version: 1.0.8
Summary: MalNetLib is a Python library for parsing PE files made with .NET
Home-page: https://github.com/xanhacks/malnetlib
Author: xanhacks
Keywords: dotnet,parser
